{
	"KAGUYA-OX_DEMON.name": "Ox Demon",
	"KAGUYA-OX_DEMON.moves.ENRAGE.title": "Enrage",
	"KAGUYA-OX_DEMON.moves.ENRAGE.banter": "!!!!",
	"KAGUYA-OX_DEMON.moves.SKULL_BASH.title": "Skull Bash",
	"KAGUYA-OX_DEMON.moves.CHARGE.title": "Ox Charge",
	"KAGUYA-OX_DEMON_ARTHROPOD.name": "Ox Demon (Arthropod Type)",
	"KAGUYA-OX_DEMON_ARTHROPOD.moves.COMBO.title": "Combo",
	"KAGUYA-OX_DEMON_ARTHROPOD.moves.MUTILATE.title": "Mutilate",
	"KAGUYA-OX_DEMON_ARTHROPOD.moves.RIP.title": "Rip",
	"KAGUYA-TSUKIBITO.name": "Tsukito (Two-Mountain Type)",
	"KAGUYA-TSUKIBITO.moves.COMBO.title": "Combo",
	"KAGUYA-TSUKIBITO.moves.REGEN.title": "Regenerate",
	"KAGUYA-TSUKIBITO2.name": "Tsukito (Two-Mountain Type)",
	"KAGUYA-TSUKIBITO2.moves.COMBO.title": "Combo",
	"KAGUYA-TSUKIBITO2.moves.REGEN.title": "Regenerate",
	"KAGUYA-IRO_P.name": "Iro P",
	"KAGUYA-IRO_P.moves.BUFF.title": "Buff",
	"KAGUYA-IRO_P.moves.RISING_DRAGON.title": "Rising Dragon",
	"KAGUYA-IRO_P.moves.PARRY.title": "Parry",
	"KAGUYA-TEIMEI.name": "Teimei",
	"KAGUYA-TEIMEI.moves.BUFF.title": "Buff",
	"KAGUYA-TEIMEI.moves.HEAVY.title": "Heavy Strike",
	"KAGUYA-TEIMEI.moves.COMBO.title": "Combo",
	"KAGUYA-THUNDER.name": "Lei",
	"KAGUYA-THUNDER.moves.BINDING_TRAP.title": "Binding Trap",
	"KAGUYA-THUNDER.moves.MINE_TRAP.title": "Landmine Trap",
	"KAGUYA-THUNDER.moves.HEAVY_ATTACK.title": "Thunderous Heavy Strike",
	"KAGUYA-NAY.name": "Nai",
	"KAGUYA-NAY.moves.LIGHTNING_ARROW.title": "Lightning Arrow",
	"KAGUYA-NAY.moves.RAPID_SHOT.title": "Rapid Shot",
	"KAGUYA-TSUKITO_BAG.name": "Tsukito · Bag Type",
	"KAGUYA-TSUKITO_BAG.moves.SMASH.title": "Smash",
	"KAGUYA-TSUKITO_BAG.moves.CHARGE.title": "Charge",
	"KAGUYA-TSUKITO_BAG.moves.SCATTER.title": "Scatter",
	"KAGUYA-TSUKITO_TENCHU.name": "Tsukito · Celestial Maiden Type",
	"KAGUYA-TSUKITO_TENCHU.moves.CHAOS_SOUND.title": "Chaos Sound",
	"KAGUYA-TSUKITO_TENCHU.moves.HARMONY.title": "Harmony",
	"KAGUYA-TSUKITO_TENCHU.moves.STRONG_TONE.title": "Strong Tone",
	"KAGUYA-TSUKITO_TENCHU.moves.LASER_CANNON.title": "Laser Cannon",
	"KAGUYA-TSUKITO_TENCHU.moves.CHARGE.title": "Charge",
	"KAGUYA-TSUKITO_TENCHU.moves.CHARGE.banter": "...!!!",
	"KAGUYA-TSUKITO_TENCHU.moves.SCATTER.title": "Scatter",
	"KAGUYA-TSUKITO_KONGO.name": "Tsukito · Vajra Type",
	"KAGUYA-TSUKITO_KONGO.moves.PUNCH.title": "Consecutive Punches",
	"KAGUYA-TSUKITO_KONGO.moves.MEGA_PUNCH.title": "Mega Punch",
	"KAGUYA-TSUKITO_KONGO.moves.GONG.title": "Gong Strike",
	"KAGUYA-TSUKITO_KONGO.moves.SOUND_STRIKE.title": "Sound Strike",
	"KAGUYA-TSUKITO_KONGO.moves.SHOCKWAVE.title": "Shockwave",
	"KAGUYA-TSUKITO_KONGO.moves.GOLDEN_BODY.title": "Golden Body",
	"KAGUYA-TSUKITO_KONGO.moves.SMASH.title": "Smash",
	"KAGUYA-TSUKITO_KONGO.moves.BLINK.title": "Blink",
	"KAGUYA-TSUKITO_KONGO.moves.ZEN.title": "Zen",
	"KAGUYA-TSUKITO_ZUISHO.name": "Tsukito · Follower Beast Type",
	"KAGUYA-TSUKITO_ZUISHO.moves.CRUSH.title": "Crush",
	"KAGUYA-TSUKITO_ZUISHO.moves.DEVOUR.title": "Devour",
	"KAGUYA-TSUKITO_ZUISHO.moves.HUNGER.title": "Hunger",
	"KAGUYA-TSUKITO_ZUISHO.moves.SLAM.title": "Slam",
	"KAGUYA-TSUKITO_ZUISHO.moves.SLASH.title": "Slash",
	"KAGUYA-TSUKITO_ZUISHO.moves.CLASH.title": "Clash",
	"KAGUYA-TSUKITO_ZUISHO.moves.RAGE.title": "Rage",
	"KAGUYA-TSUKITO_TENCHU_SINGLE.name": "Tsukito · Celestial Maiden Type",
	"KAGUYA-TSUKITO_BAG_SINGLE.name": "Tsukito · Bag Type",
	"KAGUYA-TSUKITO_ZUISHO_SINGLE.name": "Tsukito · Follower Beast Type",
	"KAGUYA-TSUKITO_KONGO_TWO_PHASE.name": "Tsukito · Vajra Type",
	"KAGUYA-TSUKITO_BOSATSU.name": "Tsukito · Bodhisattva Type",
	"KAGUYA-TSUKITO_BOSATSU.moves.START.title": "Start",
	"KAGUYA-TSUKITO_BOSATSU.moves.MAJESTY.title": "Majesty",
	"KAGUYA-TSUKITO_BOSATSU.moves.BIND.title": "Bind",
	"KAGUYA-TSUKITO_BOSATSU.moves.GAZE.title": "Gaze",
	"KAGUYA-TSUKITO_BOSATSU.moves.DESPAIR.title": "Despair",
	"KAGUYA-TSUKITO_BOSATSU.moves.ENCOURAGE.title": "Encourage",
	"KAGUYA-TSUKITO_BOSATSU.moves.REVIVE.title": "Revive",
	"KAGUYA-TSUKITO_BOSATSU.moves.ANNIHILATION.title": "Annihilation",
	"KAGUYA-TSUKITO_TENCHU_PHASE2_ONLY.name": "Tsukito · Celestial Maiden Type",
	"KAGUYA-TSUKITO_TENCHU_PHASE2_ONLY.moves.CHARGE.title": "Charge",
	"KAGUYA-TSUKITO_KONGO_PHASE3_ONLY.name": "Tsukito · Vajra Type",
	"KAGUYA-TSUKITO_ZUISHO_PHASE2_ONLY.name": "Tsukito · Follower Beast Type",
	"KAGUYA-TSUKITO_KONGO.moves.BACK_TO_WALL.banter": "...?!",
	"KAGUYA-TSUKITO_TENCHU.moves.BACK_TO_WALL.banter": "?",
	"KAGUYA-BATTLE_SOLDIER_A.name": "Battle Soldier A",
	"KAGUYA-BATTLE_SOLDIER_A.moves.ASSAULT.title": "Assault",
	"KAGUYA-BATTLE_SOLDIER_A.moves.GUARD.title": "Guard",
	"KAGUYA-BATTLE_SOLDIER_B.name": "Battle Soldier B",
	"KAGUYA-BATTLE_SOLDIER_B.moves.ENCOURAGE.title": "Encourage",
	"KAGUYA-BATTLE_SOLDIER_B.moves.GONG.title": "Gong Strike",
	"KAGUYA-KAGUYA_PET.name": "Kaguya Pet",
	"KAGUYA-KAGUYA_PET.moves.IDLE.title": "Follow"
}
